lylib/__init__.py
lylib/system.py
lylib_LyraMakes-0.0.1.dist-info/LICENSE
lylib_LyraMakes-0.0.1.dist-info/METADATA
lylib_LyraMakes-0.0.1.dist-info/WHEEL
lylib_LyraMakes-0.0.1.dist-info/top_level.txt
lylib_LyraMakes-0.0.1.dist-info/RECORD
