Metadata-Version: 2.1
Name: lylib-LyraMakes
Version: 0.0.1
Summary: A package containing functions that I frequently use
Home-page: UNKNOWN
Author: Lyra Brooke Brown
Author-email: blyra05@gmail.com
License: UNKNOWN
Platform: UNKNOWN
Classifier: Programming Language :: Python :: 3
Classifier: License :: OSI Approved :: MIT License
Classifier: Operating System :: OS Independent
Requires-Python: >=3.6
License-File: LICENSE
